md2doc/__init__.py
md2doc/api_client.py
md2doc/models.py
md2doc/server.py
md2doc-0.1.3.dist-info/METADATA
md2doc-0.1.3.dist-info/WHEEL
md2doc-0.1.3.dist-info/entry_points.txt
md2doc-0.1.3.dist-info/RECORD
