Metadata-Version: 2.4
Name: md2doc
Version: 0.1.3
Summary: Markdown to DOCX conversion MCP Server
Project-URL: Homepage, https://github.com/Yorick-Ryu/md2doc-mcp
Project-URL: Issues, https://github.com/Yorick-Ryu/md2doc-mcp/issues
Author-email: Yorick <yurui0216@gmail.com>
License: MIT
Keywords: conversion,docx,markdown,mcp,model-context-protocol
Classifier: Development Status :: 4 - Beta
Classifier: Intended Audience :: Developers
Classifier: License :: OSI Approved :: MIT License
Classifier: Programming Language :: Python :: 3
Classifier: Programming Language :: Python :: 3.10
Classifier: Programming Language :: Python :: 3.11
Classifier: Programming Language :: Python :: 3.12
Classifier: Topic :: Software Development :: Libraries :: Python Modules
Classifier: Topic :: Text Processing :: Markup
Requires-Python: >=3.10
Requires-Dist: httpx>=0.25.0
Requires-Dist: mcp>=1.0.0
Requires-Dist: pydantic>=2.0.0
Provides-Extra: dev
Requires-Dist: black>=23.0.0; extra == 'dev'
Requires-Dist: isort>=5.0.0; extra == 'dev'
Requires-Dist: pytest-asyncio>=0.21.0; extra == 'dev'
Requires-Dist: pytest>=7.0.0; extra == 'dev'
